paicorelib/__init__.py
paicorelib/coordinate.py
paicorelib/framelib/__init__.py
paicorelib/framelib/base.py
paicorelib/framelib/frame_defs.py
paicorelib/framelib/frame_gen.py
paicorelib/framelib/frames.py
paicorelib/framelib/types.py
paicorelib/framelib/utils.py
paicorelib/hw_defs.py
paicorelib/ram_defs.py
paicorelib/ram_model.py
paicorelib/reg_defs.py
paicorelib/reg_model.py
paicorelib/routing_defs.py
paicorelib/utils.py
paicorelib-1.5.0.dist-info/METADATA
paicorelib-1.5.0.dist-info/WHEEL
paicorelib-1.5.0.dist-info/licenses/LICENSE
paicorelib-1.5.0.dist-info/RECORD
