Metadata-Version: 2.4
Name: paicorelib
Version: 1.5.0
Summary: Library of PAICORE
License: GPL-3.0-or-later
License-File: LICENSE
Keywords: PAIlib,PAICORE,neuromorphic-chip,brain-inspired-ai
Author: Ziru Pan
Author-email: zrpan@stu.pku.edu.cn
Maintainer: Siyuan Gao
Maintainer-email: siyuan-gao@outlook.com
Requires-Python: >=3.10
Classifier: Intended Audience :: Science/Research
Classifier: License :: OSI Approved :: GNU General Public License v3 or later (GPLv3+)
Classifier: Operating System :: OS Independent
Classifier: Programming Language :: Python :: 3 :: Only
Classifier: Programming Language :: Python :: 3.10
Classifier: Programming Language :: Python :: 3.11
Classifier: Programming Language :: Python :: 3.12
Classifier: Programming Language :: Python :: 3.13
Classifier: Topic :: Scientific/Engineering :: Artificial Intelligence
Classifier: Topic :: Software Development :: Libraries
Requires-Dist: numpy (>=2.1.0,<3.0.0)
Requires-Dist: pydantic (>=2.10.0,<3.0.0)
Project-URL: Documentation, https://github.com/PAICookers/PAIlib#readme
Project-URL: Homepage, https://github.com/PAICookers/PAIlib
Project-URL: Repository, https://github.com/PAICookers/PAIlib
